odoo/addons/account_invoice_facturx_py3o/README.rst
odoo/addons/account_invoice_facturx_py3o/__init__.py
odoo/addons/account_invoice_facturx_py3o/__manifest__.py
odoo/addons/account_invoice_facturx_py3o/i18n/account_invoice_factur-x_py3o.pot
odoo/addons/account_invoice_facturx_py3o/i18n/account_invoice_facturx_py3o.pot
odoo/addons/account_invoice_facturx_py3o/i18n/de.po
odoo/addons/account_invoice_facturx_py3o/i18n/es.po
odoo/addons/account_invoice_facturx_py3o/models/__init__.py
odoo/addons/account_invoice_facturx_py3o/models/py3o_report.py
odoo/addons/account_invoice_facturx_py3o/readme/CONTRIBUTORS.rst
odoo/addons/account_invoice_facturx_py3o/readme/DESCRIPTION.rst
odoo/addons/account_invoice_facturx_py3o/static/description/icon.png
odoo/addons/account_invoice_facturx_py3o/static/description/index.html
odoo12_addon_account_invoice_facturx_py3o-12.0.1.0.1.dist-info/METADATA
odoo12_addon_account_invoice_facturx_py3o-12.0.1.0.1.dist-info/WHEEL
odoo12_addon_account_invoice_facturx_py3o-12.0.1.0.1.dist-info/top_level.txt
odoo12_addon_account_invoice_facturx_py3o-12.0.1.0.1.dist-info/RECORD
