Metadata-Version: 2.1
Name: odoo12-addon-account_invoice_facturx_py3o
Version: 12.0.1.0.1
Summary: Generate Factur-X invoices with Py3o reporting engine
Home-page: https://github.com/OCA/edi
Author: Akretion,Odoo Community Association (OCA)
Author-email: support@odoo-community.org
License: AGPL-3
Classifier: Programming Language :: Python
Classifier: Framework :: Odoo
Classifier: Framework :: Odoo :: 12.0
Classifier: License :: OSI Approved :: GNU Affero General Public License v3
Requires-Python: >=3.5
Requires-Dist: factur-x<=3.1
Requires-Dist: odoo12-addon-account-invoice-facturx
Requires-Dist: odoo12-addon-report-py3o
Requires-Dist: odoo<12.1dev,>=12.0a
